kytodb.py
kytodb-0.2.1.dist-info/METADATA
kytodb-0.2.1.dist-info/WHEEL
kytodb-0.2.1.dist-info/licenses/LICENSE
kytodb-0.2.1.dist-info/RECORD
