Metadata-Version: 2.4
Name: kytodb
Version: 0.2.1
Summary: A simple, easy-to-use Pydantic embedded database library
Project-URL: Homepage, https://github.com/MatthewScholefield/kyto-db
Author-email: "Matthew D. Scholefield" <matthew331199@gmail.com>
License: MIT
License-File: LICENSE
Classifier: Development Status :: 3 - Alpha
Classifier: Intended Audience :: Developers
Classifier: Programming Language :: Python :: 3
Classifier: Programming Language :: Python :: 3.10
Classifier: Programming Language :: Python :: 3.11
Classifier: Programming Language :: Python :: 3.12
Requires-Python: >=3.10
Requires-Dist: pydantic>=2.9.2
Requires-Dist: rocksdb-py>=0.0.5
